components/spec.schema.json
components/duckdb.processor/spec.yaml
components/filesystem.csv_extractor/spec.yaml
components/filesystem.csv_writer/spec.yaml
components/graphql.extractor/spec.yaml
components/mysql.extractor/spec.yaml
components/mysql.writer/spec.yaml
components/posthog.extractor/spec.yaml
components/supabase.extractor/spec.yaml
components/supabase.writer/spec.yaml
osiris/__init__.py
osiris/cli/__init__.py
osiris/cli/chat.py
osiris/cli/chat_deprecation.py
osiris/cli/compile.py
osiris/cli/components_cmd.py
osiris/cli/connections_cmd.py
osiris/cli/discovery_cmd.py
osiris/cli/guide_cmd.py
osiris/cli/init.py
osiris/cli/logs.py
osiris/cli/main.py
osiris/cli/maintenance.py
osiris/cli/mcp_cmd.py
osiris/cli/mcp_entrypoint.py
osiris/cli/memory_cmd.py
osiris/cli/oml_validate.py
osiris/cli/run.py
osiris/cli/run_command.py
osiris/cli/runs.py
osiris/cli/usecases_cmd.py
osiris/cli/helpers/__init__.py
osiris/cli/helpers/connection_helpers.py
osiris/cli/helpers/session_helpers.py
osiris/cli/mcp_subcommands/__init__.py
osiris/components/__init__.py
osiris/components/error_mapper.py
osiris/components/registry.py
osiris/components/registry_validation_todo.py
osiris/components/utils.py
osiris/connectors/__init__.py
osiris/connectors/filesystem/__init__.py
osiris/connectors/filesystem/writer.py
osiris/connectors/mysql/__init__.py
osiris/connectors/mysql/client.py
osiris/connectors/mysql/extractor.py
osiris/connectors/mysql/writer.py
osiris/connectors/supabase/__init__.py
osiris/connectors/supabase/client.py
osiris/connectors/supabase/extractor.py
osiris/connectors/supabase/writer.py
osiris/core/__init__.py
osiris/core/adapter_factory.py
osiris/core/aiop_export.py
osiris/core/cache_fingerprint.py
osiris/core/canonical.py
osiris/core/compiler_v0.py
osiris/core/config.py
osiris/core/conversational_agent.py
osiris/core/discovery.py
osiris/core/driver.py
osiris/core/env_loader.py
osiris/core/error_taxonomy.py
osiris/core/execution_adapter.py
osiris/core/fingerprint.py
osiris_pipeline-0.5.7.dist-info/licenses/LICENSE
osiris_pipeline-0.5.7.dist-info/METADATA
osiris_pipeline-0.5.7.dist-info/WHEEL
osiris_pipeline-0.5.7.dist-info/entry_points.txt
osiris_pipeline-0.5.7.dist-info/top_level.txt
osiris_pipeline-0.5.7.dist-info/RECORD
