Metadata-Version: 2.4
Name: osiris-pipeline
Version: 0.5.7
Summary: LLM-first conversational ETL pipeline generator
Author-email: Osiris Project <petr@keboola.com>
License: Apache-2.0
Project-URL: Homepage, https://github.com/keboola/osiris
Project-URL: Documentation, https://github.com/keboola/osiris/tree/main/docs
Project-URL: Repository, https://github.com/keboola/osiris
Project-URL: Issues, https://github.com/keboola/osiris/issues
Project-URL: Changelog, https://github.com/keboola/osiris/blob/main/CHANGELOG.md
Keywords: etl,elt,pipeline,oml,duckdb,sql,llm,ai,conversational,data engineering,human-in-the-loop,mysql,supabase,postgres,csv,openai,claude,gemini,sql safety
Classifier: Development Status :: 3 - Alpha
Classifier: Intended Audience :: Developers
Classifier: Intended Audience :: Information Technology
Classifier: License :: OSI Approved :: Apache Software License
Classifier: Operating System :: OS Independent
Classifier: Environment :: Console
Classifier: Natural Language :: English
Classifier: Programming Language :: Python :: 3
Classifier: Programming Language :: Python :: 3.11
Classifier: Programming Language :: Python :: 3.12
Classifier: Programming Language :: Python :: 3.13
Classifier: Typing :: Typed
Classifier: Topic :: Database
Classifier: Topic :: Scientific/Engineering :: Information Analysis
Classifier: Topic :: Software Development :: Libraries :: Python Modules
Classifier: Topic :: Utilities
Requires-Python: >=3.11
License-File: LICENSE
Requires-Dist: rich>=13.0.0
Requires-Dist: pyyaml>=6.0.2
Requires-Dist: duckdb>=0.9.0
Requires-Dist: sqlalchemy>=2.0.0
Requires-Dist: pymysql>=1.1.0
Requires-Dist: supabase>=2.7.0
Requires-Dist: openai>=1.3.0
Requires-Dist: anthropic>=0.25.0
Requires-Dist: google-generativeai>=0.5.0
Requires-Dist: python-dotenv>=1.0.0
Requires-Dist: pandas>=2.0.0
Requires-Dist: jsonschema>=4.25.1
Requires-Dist: requests>=2.32.5
Requires-Dist: jsonpath-ng>=1.7.0
Provides-Extra: dev
Requires-Dist: pytest>=7.0.0; extra == "dev"
Requires-Dist: pytest-asyncio>=0.21.0; extra == "dev"
Requires-Dist: pytest-cov>=4.0.0; extra == "dev"
Requires-Dist: black>=23.0.0; extra == "dev"
Requires-Dist: mypy>=1.0.0; extra == "dev"
Requires-Dist: ruff>=0.1.0; extra == "dev"
Requires-Dist: isort>=5.12.0; extra == "dev"
Requires-Dist: pre-commit>=3.0.0; extra == "dev"
Requires-Dist: bandit[toml]>=1.7.0; extra == "dev"
Requires-Dist: detect-secrets>=1.4.0; extra == "dev"
Requires-Dist: build>=0.10.0; extra == "dev"
Requires-Dist: twine>=4.0.0; extra == "dev"
Provides-Extra: docs
Requires-Dist: mkdocs>=1.5.0; extra == "docs"
Requires-Dist: mkdocs-material>=9.0.0; extra == "docs"
Requires-Dist: mkdocs-mermaid2-plugin>=1.0.0; extra == "docs"
Dynamic: license-file
